bin/__init__.py
bin/argtypes.py
bin/calculate_nn_backprop.py
bin/calculate_stats.py
bin/correlationsAsFunc.py
bin/draw_net.py
bin/io_modules.py
bin/iomodules_tensorflow.py
bin/lasagna_cnn_definitions.py
bin/lasagna_deepmlp_definitions.py
bin/lasagna_mlp_definitions.py
bin/lasagna_transfermlp_definitions.py
bin/logistic_sgd_traintest.py
bin/map_gene_names.py
bin/normalization_functions.py
bin/plot_confusion.py
bin/plot_roc.py
bin/sampling_algorithms.py
bin/split_input_into_testtrainvalid.py
cancerscope/__init__.py
cancerscope/command_line.py
cancerscope/config.py
cancerscope/get_models.py
cancerscope/scope_ensemble.py
cancerscope/scope_ensemble_functions.py
cancerscope/scope_io_modules.py
cancerscope/scope_normalization_functions.py
cancerscope/scope_plots.py
cancerscope/todel_model_setup.py
cancerscope/todel_predict.py
cancerscope/utils.py
cancerscope/resources/._scope_features_genenames.txt
cancerscope/resources/dict_labcount_rm500.txt
cancerscope/resources/diseasetypes_codes.txt
cancerscope/resources/scope_features_genenames.txt
cancerscope/resources/scope_features_genenames_old.txt
cancerscope/resources/scope_files.txt
cancerscope-0.31.dist-info/LICENSE.txt
cancerscope-0.31.dist-info/METADATA
cancerscope-0.31.dist-info/WHEEL
cancerscope-0.31.dist-info/top_level.txt
cancerscope-0.31.dist-info/RECORD
