Metadata-Version: 2.1
Name: cancerscope
Version: 0.31
Summary: An RNA-Seq based tool for Supervised Cancer Origin Prediction using Expression
Home-page: https://pypi.org/project/cancerscope/
Author: Jasleen Grewal
Author-email: grewalj23@gmail.com
License: MIT
Platform: UNKNOWN
Classifier: Programming Language :: Python :: 2.7
Classifier: Topic :: Scientific/Engineering :: Artificial Intelligence
Classifier: Development Status :: 5 - Production/Stable
Classifier: Intended Audience :: Healthcare Industry
Classifier: Topic :: Scientific/Engineering :: Medical Science Apps.
Classifier: Topic :: Scientific/Engineering :: Bio-Informatics
Requires-Python: >=2.6,<3.0
Requires-Dist: coverage
Requires-Dist: numpy
Requires-Dist: scikit-learn (>=0.18)
Requires-Dist: scipy
Requires-Dist: plotnine
Requires-Dist: requests
Requires-Dist: pyyaml
Requires-Dist: matplotlib (<=2.2.2)
Requires-Dist: pysocks (==1.6.8)
